Metadata-Version: 2.1
Name: fixtures_extractor
Version: 0.1.0
Summary: Set of tools to extract fixtures from Django models navigating through the relationships of a given model to get a usable subset of the database.
Author-email: Mati Barriento <elmatibarriento@gmail.com>
Classifier: Programming Language :: Python :: 3
Classifier: License :: OSI Approved :: MIT License
Classifier: Operating System :: OS Independent
Requires-Dist: Django>=3.2
Project-URL: Homepage, https://github.com/matibarriento/fixtures_extractor
